{"Reporting Railroad Code":"ATK","Reporting Railroad Name":"Amtrak (National Railroad Passenger Corporation)","Report Year":"2005","Accident Number":"095483","PDF Link":"https://safetydata.fra.dot.gov/Officeofsafety/Publicsite/FORM54/F54Report.aspx?RepType=SQL&txtf54key=ATK09548320050129","Accident Year":"05","Accident Month":"01","Other Railroad Code":"CSX","Other Railroad Name":"CSX Transportation","Other Accident Number":"000010642","Other Accident Year":"05","Other Accident Month":"01","Maintenance Railroad Code":"ATK","Maintenance Railroad Name":"Amtrak (National Railroad Passenger Corporation)","Maintenance Accident Number":"095483","Maintenance Accident Year":"05","Maintenance Accident Month":"01","Grade Crossing ID":"","Day":"29","Date":"01/29/2005","Time":"8:25 PM","Accident Type Code":"01","Accident Type":"Derailment","Hazmat Cars":"0","Hazmat Cars Damaged":"0","Hazmat Released Cars":"0","Persons Evacuated":"0","Subdivision":"","Division Code":"SOU","Division":"SOU","Station":"HIALEAH","Milepost":"1033.4","State Code":"12","State Abbreviation":"FL","State Name":"FLORIDA","County Code":"25","County Name":"DADE","District":"3","Temperature":"76","Visibility Code":"4","Visibility":"Dark","Weather Condition Code":"1","Weather Condition":"Clear","Track Type Code":"2","Track Type":"Yard","Track Name":"WHEEL TRACK","Track Class":"1","Track Density":"000000","Train Direction Code":"","Train Direction":"","Equipment Type Code":"","Equipment Type":"","Equipment Attended":"","Train Number":"","Train Speed":"0","Recorded Estimated Speed":"","Maximum Speed":"5","Gross Tonnage":"0","Signalization Code":"","Signalization":"","Method of Operation Code":"L","Method of Operation":"","Adjunct Code 1":"","Adjunct Code Name 1":"","Adjunct Code 2":"","Adjunct Code Name 2":"","Adjunct Code 3":"","Adjunct Code Name 3":"","Remote Control Locomotive Code":"","Remote Control Locomotive":"","First Car Initials":"","First Car Number":"","First Car Position":"0","First Car Loaded":"","Causing Car Initials":"","Causing Car Number":"","Causing Car Position":"0","Causing Car Loaded":"","Positive Alcohol Tests":"","Positive Drug Tests":"","Passengers Transported":"","Head End Locomotives":"0","Mid Train Manual Locomotives":"0","Mid Train Remote Locomotives":"0","Rear End Manual Locomotives":"0","Rear End Remote Locomotives":"0","Derailed Head End Locomotives":"0","Derailed Mid Train Manual Locomotives":"0","Derailed Mid Train Remote Locomotives":"0","Derailed Rear End Manual Locomotives":"0","Derailed Rear End Remote Locomotives":"0","Loaded Freight Cars":"0","Loaded Passenger Cars":"0","Empty Freight Cars":"0","Empty Passenger Cars":"0","Cabooses":"0","Derailed Loaded Freight Cars":"0","Derailed Loaded Passenger Cars":"0","Derailed Empty Freight Cars":"0","Derailed Empty Passenger Cars":"0","Derailed Cabooses":"0","Equipment Damage Cost":"0","Track Damage Cost":"3600","Total Damage Cost":"46200","Primary Accident Cause Code":"H702","Primary Accident Cause":"Switch improperly lined","Contributing Accident Cause Code":"","Contributing Accident Cause":"","Accident Cause Code":"H702","Accident Cause":"Switch improperly lined","Engineers On Duty":"0","Firemen On Duty":"0","Conductors On Duty":"0","Brakemen On Duty":"0","Hours Engineers On Duty":"","Minutes Engineers On Duty":"","Hours Conductors On Duty":"","Minutes Conductors On Duty":"","Railroad Employees Killed":"0","Railroad Employees Injured":"0","Passengers Killed":"0","Passengers Injured":"0","Others Killed":"0","Others Injured":"0","Persons Killed For Reporting Railroad":"0","Persons Injured For Reporting Railroad":"0","Total Persons Killed":"0","Total Persons Injured":"0","Total Killed Form 54":"0","Total Injured Form 54":"0","Special Study 1":"","Special Study 2":"","Latitude":"0","Longitude":"0","Narrative":"A CSX SWITCH CREW WAS MOVING TRAIN 91S EQUIPMENT IN HIALEAH FACILITY FROM TRACK 3 TO TRACK 2.  CSX CONDUCTOR MISTAKENLY LINED THE MOVEMENT INTO THE WHEEL TRACK INSTEAD OF TRACK 2.  EQUIPMENT ENTERED WHEEL TRACK AND THE LEAD CAR AMT 1228 STRUCK AMT 28001, WHICH SUBSEQUENTLY STRUCK AMT 54530, WHICH SUBSEQUENTLY STRUCK AN AMTRAK TAMPER, WHICH THEN STRUCK A SUPPLY OF COACH WHEELS STORED ON THE END OFTHE TRACK.","Joint Track Type":"Yard","Joint Track Class":"1","Class Code":"1L","Class":"1L","Joint CD":"1","Incident Key":"ATK095483200501","Report Key":"ATK095483200501","Reporting Railroad Company Grouping":"Passenger (Formerly Commuter)","Reporting Railroad Class":"","Reporting Railroad SMT Grouping":"SMT-1 - Amtrak, Commuter East","Reporting Parent Railroad Company Code":"ATK","Reporting Parent Railroad Company Name":"Amtrak (National Railroad Passenger Corporation)","Reporting Railroad Holding Company":"Amtrak","Other Railroad Company Grouping":"","Other Railroad Class":"Class 1","Other Railroad SMT Grouping":"SMT-9 - CSX","Other Parent Railroad Company Code":"CSX","Other Parent Railroad Company Name":"CSX Transportation","Other Railroad Holding Company":"CSX Transportation","Maintenance Railroad Company Grouping":"Passenger (Formerly Commuter)","Maintenance Railroad Class":"","Maintenance Railroad SMT Grouping":"SMT-1 - Amtrak, Commuter East","Maintenance Parent Railroad Company Code":"ATK","Maintenance Parent Railroad Company Name":"Amtrak (National Railroad Passenger Corporation)","Maintenance Railroad Holding Company":"Amtrak"}