{"Reporting Railroad Code":"ATK","Reporting Railroad Name":"Amtrak (National Railroad Passenger Corporation)","Report Year":"2018","Accident Number":"151645","PDF Link":"https://safetydata.fra.dot.gov/Officeofsafety/Publicsite/FORM54/F54Report.aspx?RepType=SQL&txtf54key=ATK15164520180120","Accident Year":"18","Accident Month":"01","Other Railroad Code":"NJTR","Other Railroad Name":"New Jersey Transit Rail Operations","Other Accident Number":"201803137","Other Accident Year":"18","Other Accident Month":"01","Maintenance Railroad Code":"ATK","Maintenance Railroad Name":"Amtrak (National Railroad Passenger Corporation)","Maintenance Accident Number":"151645","Maintenance Accident Year":"18","Maintenance Accident Month":"01","Grade Crossing ID":"","Day":"20","Date":"01/20/2018","Time":"6:38 AM","Accident Type Code":"13","Accident Type":"Other (describe in narrative)","Hazmat Cars":"0","Hazmat Cars Damaged":"0","Hazmat Released Cars":"0","Persons Evacuated":"0","Subdivision":"NEC","Division Code":"","Division":"","Station":"WEEHAWKEN","Milepost":"0002.9","State Code":"34","State Abbreviation":"NJ","State Name":"NEW JERSEY","County Code":"17","County Name":"HUDSON","District":"1","Temperature":"30","Visibility Code":"2","Visibility":"Day","Weather Condition Code":"1","Weather Condition":"Clear","Track Type Code":"1","Track Type":"Main","Track Name":"2","Track Class":"3","Track Density":"000013","Train Direction Code":"","Train Direction":"","Equipment Type Code":"","Equipment Type":"","Equipment Attended":"","Train Number":"","Train Speed":"0","Recorded Estimated Speed":"","Maximum Speed":"45","Gross Tonnage":"0","Signalization Code":"1","Signalization":"Signaled","Method of Operation Code":"","Method of Operation":"Signal Indication","Adjunct Code 1":"A","Adjunct Code Name 1":"Auto Cab Signals","Adjunct Code 2":"D","Adjunct Code Name 2":"Automatic Block Signals System","Adjunct Code 3":"Q","Adjunct Code Name 3":"Traffic Control System/CTC","Remote Control Locomotive Code":"","Remote Control Locomotive":"","First Car Initials":"","First Car Number":"","First Car Position":"0","First Car Loaded":"","Causing Car Initials":"","Causing Car Number":"","Causing Car Position":"0","Causing Car Loaded":"","Positive Alcohol Tests":"","Positive Drug Tests":"","Passengers Transported":"","Head End Locomotives":"0","Mid Train Manual Locomotives":"0","Mid Train Remote Locomotives":"0","Rear End Manual Locomotives":"0","Rear End Remote Locomotives":"0","Derailed Head End Locomotives":"0","Derailed Mid Train Manual Locomotives":"0","Derailed Mid Train Remote Locomotives":"0","Derailed Rear End Manual Locomotives":"0","Derailed Rear End Remote Locomotives":"0","Loaded Freight Cars":"0","Loaded Passenger Cars":"0","Empty Freight Cars":"0","Empty Passenger Cars":"0","Cabooses":"0","Derailed Loaded Freight Cars":"0","Derailed Loaded Passenger Cars":"0","Derailed Empty Freight Cars":"0","Derailed Empty Passenger Cars":"0","Derailed Cabooses":"0","Equipment Damage Cost":"0","Track Damage Cost":"20000","Total Damage Cost":"31150","Primary Accident Cause Code":"T404","Primary Accident Cause":"Catenary system defect","Contributing Accident Cause Code":"","Contributing Accident Cause":"","Accident Cause Code":"T404","Accident Cause":"Catenary system defect","Engineers On Duty":"0","Firemen On Duty":"0","Conductors On Duty":"0","Brakemen On Duty":"0","Hours Engineers On Duty":"","Minutes Engineers On Duty":"","Hours Conductors On Duty":"","Minutes Conductors On Duty":"","Railroad Employees Killed":"0","Railroad Employees Injured":"0","Passengers Killed":"0","Passengers Injured":"0","Others Killed":"0","Others Injured":"0","Persons Killed For Reporting Railroad":"0","Persons Injured For Reporting Railroad":"0","Total Persons Killed":"0","Total Persons Injured":"0","Total Killed Form 54":"0","Total Injured Form 54":"0","Special Study 1":"CWR","Special Study 2":"","Latitude":"40.771329000000001","Longitude":"-74.041974999999994","Narrative":"NJT 7804 REPORTED STRIKING AN OBJECT IN THE CATENARY WHILE OPERATING NO.2 TRACK (SOUTH TUBE).  A HOLD WAS PLACED IN EFFECT CREATING A SINGLE TRACK OPERATION VIA THE NORTH TUBE BETWEEN \"A\" AND BERGEN (MP-3.7).  UPON INSPECTION MESSENGER WIRE WAS REPORTED DOWN.","Joint Track Type":"Main","Joint Track Class":"3","Class Code":"No","Class":"No","Joint CD":"1","Incident Key":"ATK151645201801","Report Key":"ATK151645201801","Reporting Railroad Company Grouping":"Passenger (Formerly Commuter)","Reporting Railroad Class":"","Reporting Railroad SMT Grouping":"SMT-1 - Amtrak, Commuter East","Reporting Parent Railroad Company Code":"ATK","Reporting Parent Railroad Company Name":"Amtrak (National Railroad Passenger Corporation)","Reporting Railroad Holding Company":"Amtrak","Other Railroad Company Grouping":"Passenger (Formerly Commuter)","Other Railroad Class":"Class 3","Other Railroad SMT Grouping":"SMT-1 - Amtrak, Commuter East","Other Parent Railroad Company Code":"NJTR","Other Parent Railroad Company Name":"New Jersey Transit Rail Operations","Other Railroad Holding Company":"Not Assigned","Maintenance Railroad Company Grouping":"Passenger (Formerly Commuter)","Maintenance Railroad Class":"","Maintenance Railroad SMT Grouping":"SMT-1 - Amtrak, Commuter East","Maintenance Parent Railroad Company Code":"ATK","Maintenance Parent Railroad Company Name":"Amtrak (National Railroad Passenger Corporation)","Maintenance Railroad Holding Company":"Amtrak"}