{"Reporting Railroad Code":"ICG","Reporting Railroad Name":"Illinois Central Gulf Railroad Company","Report Year":"1975","Accident Number":"16852","PDF Link":"https://safetydata.fra.dot.gov/Officeofsafety/Publicsite/FORM54/F54Report.aspx?RepType=SQL&txtf54key=ICG1685219751119","Accident Year":"75","Accident Month":"11","Other Railroad Code":"ATK","Other Railroad Name":"Amtrak (National Railroad Passenger Corporation)","Other Accident Number":"111975A","Other Accident Year":"75","Other Accident Month":"11","Maintenance Railroad Code":"ICG","Maintenance Railroad Name":"Illinois Central Gulf Railroad Company","Maintenance Accident Number":"16852","Maintenance Accident Year":"75","Maintenance Accident Month":"11","Grade Crossing ID":"290487J","Day":"19","Date":"11/19/1975","Time":"9:08 AM","Accident Type Code":"07","Accident Type":"Hwy-rail crossing","Hazmat Cars":"0","Hazmat Cars Damaged":"0","Hazmat Released Cars":"0","Persons Evacuated":"0","Subdivision":"","Division Code":"??????","Division":"MISSOURI","Station":"ELWOOD","Milepost":"44.0","State Code":"17","State Abbreviation":"IL","State Name":"ILLINOIS","County Code":"197","County Name":"WILL","District":"4","Temperature":"50","Visibility Code":"2","Visibility":"Day","Weather Condition Code":"1","Weather Condition":"Clear","Track Type Code":"1","Track Type":"Main","Track Name":"SINGLE MAINLINE","Track Class":"4","Track Density":"6.29","Train Direction Code":"2","Train Direction":"South","Equipment Type Code":"2","Equipment Type":"Passenger Train - Pulling","Equipment Attended":"","Train Number":"301","Train Speed":"73","Recorded Estimated Speed":"Estimated","Maximum Speed":"73","Gross Tonnage":"0","Signalization Code":"","Signalization":"","Method of Operation Code":"E","Method of Operation":"","Adjunct Code 1":"","Adjunct Code Name 1":"","Adjunct Code 2":"","Adjunct Code Name 2":"","Adjunct Code 3":"","Adjunct Code Name 3":"","Remote Control Locomotive Code":"","Remote Control Locomotive":"","First Car Initials":"ATK","First Car Number":"000066","First Car Position":"2","First Car Loaded":"","Causing Car Initials":"","Causing Car Number":"","Causing Car Position":"","Causing Car Loaded":"","Positive Alcohol Tests":"","Positive Drug Tests":"","Passengers Transported":"Yes","Head End Locomotives":"1","Mid Train Manual Locomotives":"0","Mid Train Remote Locomotives":"0","Rear End Manual Locomotives":"0","Rear End Remote Locomotives":"1","Derailed Head End Locomotives":"0","Derailed Mid Train Manual Locomotives":"0","Derailed Mid Train Remote Locomotives":"0","Derailed Rear End Manual Locomotives":"0","Derailed Rear End Remote Locomotives":"1","Loaded Freight Cars":"0","Loaded Passenger Cars":"5","Empty Freight Cars":"0","Empty Passenger Cars":"0","Cabooses":"0","Derailed Loaded Freight Cars":"0","Derailed Loaded Passenger Cars":"3","Derailed Empty Freight Cars":"0","Derailed Empty Passenger Cars":"0","Derailed Cabooses":"0","Equipment Damage Cost":"1000000","Track Damage Cost":"3500","Total Damage Cost":"2007000","Primary Accident Cause Code":"M399","Primary Accident Cause":"Other causes (Provide detailed description in narrative)","Contributing Accident Cause Code":"","Contributing Accident Cause":"","Accident Cause Code":"M399","Accident Cause":"Other causes (Provide detailed description in narrative)","Engineers On Duty":"","Firemen On Duty":"","Conductors On Duty":"","Brakemen On Duty":"","Hours Engineers On Duty":"","Minutes Engineers On Duty":"","Hours Conductors On Duty":"","Minutes Conductors On Duty":"","Railroad Employees Killed":"0","Railroad Employees Injured":"0","Passengers Killed":"0","Passengers Injured":"34","Others Killed":"0","Others Injured":"1","Persons Killed For Reporting Railroad":"0","Persons Injured For Reporting Railroad":"35","Total Persons Killed":"0","Total Persons Injured":"39","Total Killed Form 54":"0","Total Injured Form 54":"35","Special Study 1":"","Special Study 2":"","Latitude":"","Longitude":"","Narrative":"NoneNoneNoneNoneNoneNoneNoneNoneNoneNoneNoneNoneNoneNoneNone","Joint Track Type":"Main","Joint Track Class":"4","Class Code":"1L","Class":"1L","Joint CD":"2","Incident Key":"ICG16852197511","Report Key":"ICG16852197511","Reporting Railroad Company Grouping":"","Reporting Railroad Class":"Class 1","Reporting Railroad SMT Grouping":"SMT-4 - CP/CN/CCD","Reporting Parent Railroad Company Code":"CN","Reporting Parent Railroad Company Name":"Canadian National - North America","Reporting Railroad Holding Company":"Canadian National - North America","Other Railroad Company Grouping":"Passenger (Formerly Commuter)","Other Railroad Class":"","Other Railroad SMT Grouping":"SMT-1 - Amtrak, Commuter East","Other Parent Railroad Company Code":"ATK","Other Parent Railroad Company Name":"Amtrak (National Railroad Passenger Corporation)","Other Railroad Holding Company":"Amtrak","Maintenance Railroad Company Grouping":"","Maintenance Railroad Class":"Class 1","Maintenance Railroad SMT Grouping":"SMT-4 - CP/CN/CCD","Maintenance Parent Railroad Company Code":"CN","Maintenance Parent Railroad Company Name":"Canadian National - North America","Maintenance Railroad Holding Company":"Canadian National - North America"}