{"Reporting Railroad Code":"PATH","Reporting Railroad Name":"Port Authority Trans Hudson","Report Year":"2020","Accident Number":"I020120","PDF Link":"https://safetydata.fra.dot.gov/Officeofsafety/Publicsite/FORM54/F54Report.aspx?RepType=SQL&txtf54key=PATHI02012020200201","Accident Year":"20","Accident Month":"02","Other Railroad Code":"","Other Railroad Name":"","Other Accident Number":"","Other Accident Year":"","Other Accident Month":"","Maintenance Railroad Code":"PATH","Maintenance Railroad Name":"Port Authority Trans Hudson","Maintenance Accident Number":"I020120","Maintenance Accident Year":"20","Maintenance Accident Month":"02","Grade Crossing ID":"","Day":"01","Date":"02/01/2020","Time":"11:19 AM","Accident Type Code":"13","Accident Type":"Other (describe in narrative)","Hazmat Cars":"0","Hazmat Cars Damaged":"0","Hazmat Released Cars":"0","Persons Evacuated":"0","Subdivision":"SYSTEM","Division Code":"","Division":"","Station":"JERSEY CITY","Milepost":"","State Code":"34","State Abbreviation":"NJ","State Name":"NEW JERSEY","County Code":"17","County Name":"HUDSON","District":"1","Temperature":"42","Visibility Code":"2","Visibility":"Day","Weather Condition Code":"2","Weather Condition":"Cloudy","Track Type Code":"1","Track Type":"Main","Track Name":"H & G","Track Class":"3","Track Density":"39.093","Train Direction Code":"4","Train Direction":"West","Equipment Type Code":"D","Equipment Type":"EMU","Equipment Attended":"Yes","Train Number":"5712","Train Speed":"50","Recorded Estimated Speed":"Estimated","Maximum Speed":"50","Gross Tonnage":"0","Signalization Code":"1","Signalization":"Signaled","Method of Operation Code":"","Method of Operation":"Signal Indication","Adjunct Code 1":"","Adjunct Code Name 1":"","Adjunct Code 2":"","Adjunct Code Name 2":"","Adjunct Code 3":"","Adjunct Code Name 3":"","Remote Control Locomotive Code":"0","Remote Control Locomotive":"Not a remotely controlled operation","First Car Initials":"PATH","First Car Number":"005712","First Car Position":"5","First Car Loaded":"Yes","Causing Car Initials":"PATH","Causing Car Number":"005712","Causing Car Position":"5","Causing Car Loaded":"Yes","Positive Alcohol Tests":"","Positive Drug Tests":"","Passengers Transported":"Yes","Head End Locomotives":"0","Mid Train Manual Locomotives":"0","Mid Train Remote Locomotives":"0","Rear End Manual Locomotives":"0","Rear End Remote Locomotives":"0","Derailed Head End Locomotives":"0","Derailed Mid Train Manual Locomotives":"0","Derailed Mid Train Remote Locomotives":"0","Derailed Rear End Manual Locomotives":"0","Derailed Rear End Remote Locomotives":"0","Loaded Freight Cars":"0","Loaded Passenger Cars":"8","Empty Freight Cars":"0","Empty Passenger Cars":"0","Cabooses":"0","Derailed Loaded Freight Cars":"0","Derailed Loaded Passenger Cars":"0","Derailed Empty Freight Cars":"0","Derailed Empty Passenger Cars":"0","Derailed Cabooses":"0","Equipment Damage Cost":"28966","Track Damage Cost":"93958","Total Damage Cost":"122924","Primary Accident Cause Code":"H995","Primary Accident Cause":"Human Factor - motive power and equipment","Contributing Accident Cause Code":"E59C","Contributing Accident Cause":"Other axle and journal bearing defects (CAR) (Provide detailed description in narrative)","Accident Cause Code":"H995","Accident Cause":"Human Factor - motive power and equipment","Engineers On Duty":"1","Firemen On Duty":"","Conductors On Duty":"1","Brakemen On Duty":"","Hours Engineers On Duty":"1","Minutes Engineers On Duty":"19","Hours Conductors On Duty":"1","Minutes Conductors On Duty":"19","Railroad Employees Killed":"0","Railroad Employees Injured":"0","Passengers Killed":"0","Passengers Injured":"0","Others Killed":"0","Others Injured":"0","Persons Killed For Reporting Railroad":"0","Persons Injured For Reporting Railroad":"0","Total Persons Killed":"0","Total Persons Injured":"0","Total Killed Form 54":"0","Total Injured Form 54":"0","Special Study 1":"OTH","Special Study 2":"000-000-000","Latitude":"40.724254999999999","Longitude":"-74.055107000000007","Narrative":"ON FEBRUARY 1, 2020 AT 11:19 AM CAR 5712 WHICH WAS PART OF CONSIST (5754-5159-5746-5688-5712-5610-5177-5741) DAMAGED THE RUNNING RAIL IMPEDIANCE BONDS WHEN THE AXLE FROZE IN THE TRACKPAK. THE FROZEN AXLE FLATTENED THE WHEEL AND THE WHEEL FLANGE SHEARED OVER 300 IMPEDIANCE BONDS OF THE SIDES OF THE RAIL BETWEEN EXCHANGE PLACE AND KEARNY POCKET ON BOTH TRACK G AND TRACK H. CONTROL CENTER BECAME AWARE OF THE ISSUE WHEN MULTIPLE TRACK SECTIONS STARTED GOING DOWN. AN OIL LEAK IN THE TRACKPAK CAUSED EXCESSIVE HEAT TO BUILD UP IN THE AXLE AND SEIZE IN PLACE.\r\nAMENDED ON 2-11-2020 FOR INCREASE IN THETOTAL COST OF THE ESTIMATE OF REPAIRS.\r\nAMENDED ON 2-18-2020 FOR INCREASE IN THE TOTAL COST OF THE ESTIMATE OF REPAIRS.\r\nAMENDED ON 3-3-2020 FOR INCREASE IN THE TOTAL COST OF THE ESTIMATE OF REPAIRS.AMENDED ON 4-23-2020 FOR FRA TRACK CLASS, SUBDIVISION AND FIELD 31C\r\nAMENDED ON 5-11-2020 FOR CHANGE IN PRIMARY CAUSE AND CONTRIBUTING CAUSE CODES. CAR EQUIPMENT DIVISION CAR INSPECTOR ASSUMED RESPONSIBILITY FOR A MISSING OIL DRAIN PLUG IN THE GEAR BOX.\r\nAMENDED ON 9-28-2020 FIELD 14 UPDATED","Joint Track Type":"Main","Joint Track Class":"3","Class Code":"No","Class":"No","Joint CD":"1","Incident Key":"PATHI020120202002","Report Key":"PATHI020120202002","Reporting Railroad Company Grouping":"Passenger (Formerly Commuter)","Reporting Railroad Class":"Class 3","Reporting Railroad SMT Grouping":"SMT-1 - Amtrak, Commuter East","Reporting Parent Railroad Company Code":"PATH","Reporting Parent Railroad Company Name":"Port Authority Trans Hudson","Reporting Railroad Holding Company":"Not Assigned","Other Railroad Company Grouping":"","Other Railroad Class":"","Other Railroad SMT Grouping":"","Other Parent Railroad Company Code":"","Other Parent Railroad Company Name":"","Other Railroad Holding Company":"","Maintenance Railroad Company Grouping":"Passenger (Formerly Commuter)","Maintenance Railroad Class":"Class 3","Maintenance Railroad SMT Grouping":"SMT-1 - Amtrak, Commuter East","Maintenance Parent Railroad Company Code":"PATH","Maintenance Parent Railroad Company Name":"Port Authority Trans Hudson","Maintenance Railroad Holding Company":"Not Assigned"}