{"Reporting Railroad Code":"BNSF","Reporting Railroad Name":"BNSF Railway Company","Report Year":"2002","Accident Number":"NW0102100","PDF Link":"https://safetydata.fra.dot.gov/Officeofsafety/Publicsite/FORM54/F54Report.aspx?RepType=SQL&txtf54key=BNSFNW010210020020101","Accident Year":"02","Accident Month":"01","Other Railroad Code":"ATK","Other Railroad Name":"Amtrak (National Railroad Passenger Corporation)","Other Accident Number":"071658","Other Accident Year":"02","Other Accident Month":"01","Maintenance Railroad Code":"BNSF","Maintenance Railroad Name":"BNSF Railway Company","Maintenance Accident Number":"NW0102100","Maintenance Accident Year":"02","Maintenance Accident Month":"01","Grade Crossing ID":"","Day":"01","Date":"01/01/2002","Time":"7:05 PM","Accident Type Code":"09","Accident Type":"Obstruction","Hazmat Cars":"0","Hazmat Cars Damaged":"0","Hazmat Released Cars":"0","Persons Evacuated":"0","Subdivision":"","Division Code":"","Division":"NORTHWEST","Station":"KALAMA","Milepost":"106.5","State Code":"53","State Abbreviation":"WA","State Name":"WASHINGTON","County Code":"15","County Name":"COWLITZ","District":"8","Temperature":"43","Visibility Code":"4","Visibility":"Dark","Weather Condition Code":"2","Weather Condition":"Cloudy","Track Type Code":"1","Track Type":"Main","Track Name":"MAIN","Track Class":"5","Track Density":"","Train Direction Code":"","Train Direction":"","Equipment Type Code":"","Equipment Type":"","Equipment Attended":"","Train Number":"","Train Speed":"0","Recorded Estimated Speed":"","Maximum Speed":"79","Gross Tonnage":"0","Signalization Code":"","Signalization":"","Method of Operation Code":"","Method of Operation":"","Adjunct Code 1":"","Adjunct Code Name 1":"","Adjunct Code 2":"","Adjunct Code Name 2":"","Adjunct Code 3":"","Adjunct Code Name 3":"","Remote Control Locomotive Code":"","Remote Control Locomotive":"","First Car Initials":"","First Car Number":"","First Car Position":"0","First Car Loaded":"","Causing Car Initials":"","Causing Car Number":"","Causing Car Position":"0","Causing Car Loaded":"","Positive Alcohol Tests":"","Positive Drug Tests":"","Passengers Transported":"","Head End Locomotives":"0","Mid Train Manual Locomotives":"0","Mid Train Remote Locomotives":"0","Rear End Manual Locomotives":"0","Rear End Remote Locomotives":"0","Derailed Head End Locomotives":"0","Derailed Mid Train Manual Locomotives":"0","Derailed Mid Train Remote Locomotives":"0","Derailed Rear End Manual Locomotives":"0","Derailed Rear End Remote Locomotives":"0","Loaded Freight Cars":"0","Loaded Passenger Cars":"0","Empty Freight Cars":"0","Empty Passenger Cars":"0","Cabooses":"0","Derailed Loaded Freight Cars":"0","Derailed Loaded Passenger Cars":"0","Derailed Empty Freight Cars":"0","Derailed Empty Passenger Cars":"0","Derailed Cabooses":"0","Equipment Damage Cost":"0","Track Damage Cost":"0","Total Damage Cost":"32380","Primary Accident Cause Code":"M402","Primary Accident Cause":"Object or equipment on or fouling track (motor vehicle - other than highway-rail crossing)","Contributing Accident Cause Code":"","Contributing Accident Cause":"","Accident Cause Code":"M402","Accident Cause":"Object or equipment on or fouling track (motor vehicle - other than highway-rail crossing)","Engineers On Duty":"","Firemen On Duty":"","Conductors On Duty":"","Brakemen On Duty":"","Hours Engineers On Duty":"","Minutes Engineers On Duty":"","Hours Conductors On Duty":"","Minutes Conductors On Duty":"","Railroad Employees Killed":"0","Railroad Employees Injured":"0","Passengers Killed":"0","Passengers Injured":"0","Others Killed":"0","Others Injured":"0","Persons Killed For Reporting Railroad":"0","Persons Injured For Reporting Railroad":"0","Total Persons Killed":"0","Total Persons Injured":"0","Total Killed Form 54":"0","Total Injured Form 54":"0","Special Study 1":"","Special Study 2":"","Latitude":"0","Longitude":"0","Narrative":"AMTRACK CREW REPORTED STRIKING A PICKUP WHICH WAS DRIVING SOUTHBOUND BETWEEN THE TWO MAIN TRACKS ATMP 1065., KALAMA, WA.  PICKUP FOULED BOTH MAINS AFTER BEING STRUCK BY THE TRAIN.NoneNoneNoneNoneNoneNoneNoneNoneNoneNoneNoneNoneNone","Joint Track Type":"Main","Joint Track Class":"4","Class Code":"1","Class":"1","Joint CD":"2","Incident Key":"BNSFNW0102100200201","Report Key":"BNSFNW0102100200201","Reporting Railroad Company Grouping":"","Reporting Railroad Class":"Class 1","Reporting Railroad SMT Grouping":"SMT-5 - BNSF","Reporting Parent Railroad Company Code":"BNSF","Reporting Parent Railroad Company Name":"BNSF Railway Company","Reporting Railroad Holding Company":"BNSF Railway Company","Other Railroad Company Grouping":"Passenger (Formerly Commuter)","Other Railroad Class":"","Other Railroad SMT Grouping":"SMT-1 - Amtrak, Commuter East","Other Parent Railroad Company Code":"ATK","Other Parent Railroad Company Name":"Amtrak (National Railroad Passenger Corporation)","Other Railroad Holding Company":"Amtrak","Maintenance Railroad Company Grouping":"","Maintenance Railroad Class":"Class 1","Maintenance Railroad SMT Grouping":"SMT-5 - BNSF","Maintenance Parent Railroad Company Code":"BNSF","Maintenance Parent Railroad Company Name":"BNSF Railway Company","Maintenance Railroad Holding Company":"BNSF Railway Company"}